opentestbed/__init__.py
opentestbed/opentestbed.py
opentestbed/opentestbed_pb2.py
opentestbed/opentestbed_pb2_grpc.py
opentestbed-0.0.4.dist-info/METADATA
opentestbed-0.0.4.dist-info/WHEEL
opentestbed-0.0.4.dist-info/top_level.txt
opentestbed-0.0.4.dist-info/RECORD
