Metadata-Version: 2.1
Name: opentestbed
Version: 0.0.4
Summary: The Open testbed Python Package
Home-page: https://github.com/open-traffic-generator/opentestbed
Author: Open Traffic Generator
Author-email: anish.gottapu@keysight.com
License: MIT
Keywords: OTG testbed for testbed reservation
Classifier: Development Status :: 3 - Alpha
Classifier: Intended Audience :: Developers
Classifier: Topic :: Software Development :: Testing :: Traffic Generation
Classifier: License :: OSI Approved :: MIT License
Classifier: Programming Language :: Python :: 2.7
Classifier: Programming Language :: Python :: 3
Requires-Python: >=2.7, <4
Requires-Dist: PyYAML
Requires-Dist: requests
Requires-Dist: semantic-version
Requires-Dist: urllib3
Requires-Dist: grpcio ~=1.35.0 ; python_version <= "3.6"
Requires-Dist: grpcio-tools ~=1.35.0 ; python_version <= "3.6"
Requires-Dist: protobuf ~=3.15.0 ; python_version <= "3.6"
Requires-Dist: grpcio-tools ~=1.59.0 ; python_version > "3.6"
Requires-Dist: grpcio ~=1.59.0 ; python_version > "3.6"
Requires-Dist: protobuf ~=4.24.4 ; python_version > "3.6"
